{
  "appPageId" : "646bbbbe-87cb-4325-a9b5-935b5b9543c0",
  "componentName" : "siteforce:sldsOneColLayout",
  "id" : "a8197314-538d-4d18-9d6c-62306a37c129",
  "label" : "ssologin2 - passwordless",
  "regions" : [ {
    "components" : [ {
      "componentAttributes" : {
        "richTextValue" : "<div align=CENTER >\n\n    <br/>&nbsp;&nbsp;&nbsp;\n<button class=\"usa-button\" style=\"width:145px\"><a href=\"/s/pwless\" style=\"color:white;font-weight:bold;font-size:16px;\">Non HHS User</a></button>    \n</div>\n<br />"
      },
      "componentName" : "forceCommunity:htmlBlock",
      "id" : "93b28cae-e013-4ccb-9a5b-f8ea19f08f8a",
      "renderPriority" : "NEUTRAL",
      "renditionMap" : { },
      "type" : "component"
    } ],
    "id" : "d9ef0905-d896-452c-a969-d8b3706c160f",
    "regionName" : "header",
    "type" : "region"
  }, {
    "components" : [ {
      "componentAttributes" : {
        "richTextValue" : "<div align=CENTER >\n\n    <br/>&nbsp;&nbsp;&nbsp;\n<button class=\"usa-button usa-button--accent-warm\" style=\"width:129px\"><a href=\"/services/auth/sso/HHS_Users\" style=\"color:white;font-weight:bold;font-size:16px;\">HHS User</a></button>    \n</div>\n<br />"
      },
      "componentName" : "forceCommunity:htmlBlock",
      "id" : "8ad4de31-ad41-4014-8d05-dfbfa230cc0e",
      "renderPriority" : "NEUTRAL",
      "renditionMap" : { },
      "type" : "component"
    } ],
    "id" : "67108c56-637d-48e4-b572-47558bbd2037",
    "regionName" : "content",
    "type" : "region"
  }, {
    "components" : [ {
      "componentAttributes" : {
        "richTextValue" : "<div align=CENTER >\n<div  style=\"align:center;width:250px\" >\nThis is a U.S. government service. Your use indicates your consent to monitoring, recording, and no expectation of privacy. Misuse is subject to criminal and civil penalties. \n<br/><a href=\"/identity/s/terms-of-service\" >Read more details. </a>\n</div>\n</div>"
      },
      "componentName" : "forceCommunity:htmlBlock",
      "id" : "fdc859b7-196a-4230-a969-e4fc10a5b193",
      "renderPriority" : "NEUTRAL",
      "renditionMap" : { },
      "type" : "component"
    } ],
    "id" : "900f01bd-37ac-4e28-9643-5a35b7b360f8",
    "regionName" : "footer",
    "type" : "region"
  }, {
    "components" : [ {
      "componentAttributes" : {
        "customHeadTags" : "",
        "description" : "",
        "title" : ""
      },
      "componentName" : "forceCommunity:seoAssistant",
      "id" : "81a1598e-b026-4a48-9a02-c974843125d0",
      "renditionMap" : { },
      "type" : "component"
    } ],
    "id" : "c30ed3e6-2b44-4c68-81db-5992a190d1ae",
    "regionName" : "sfdcHiddenRegion",
    "type" : "region"
  } ],
  "themeLayoutType" : "Login",
  "type" : "view",
  "viewType" : "login-home"
}